stopwatch_digital.v
`timescale 1ns/1ps

module clk_divider(
    input clk,
    input reset,
    output reg clk_1hz,
    output reg clk_khz
);
    reg [26:0] count_hz = 0;
    reg [16:0] count_khz = 0;

    always @(posedge clk or posedge reset) begin
        if (reset) begin
            count_hz <= 0;
            clk_1hz <= 0;
        end else begin
            count_hz <= count_hz + 1;
            if (count_hz == 5) begin
                clk_1hz <= ~clk_1hz;
                count_hz <= 0;
            end
        end
    end

    always @(posedge clk or posedge reset) begin
        if (reset) begin
            count_khz <= 0;
            clk_khz <= 0;
        end else begin
            count_khz <= count_khz + 1;
            if (count_khz == 2) begin
                clk_khz <= ~clk_khz;
                count_khz <= 0;
            end
        end
    end
endmodule

module seven_segment_decoder(
    input [3:0] digit,
    output reg [6:0] seg
);
    always @(*) begin
        case (digit)
            4'd0: seg = 7'b0000001;  // a–f on, g off
            4'd1: seg = 7'b1001111;  // b, c on
            4'd2: seg = 7'b0010010;
            4'd3: seg = 7'b0000110;
            4'd4: seg = 7'b1001100;
            4'd5: seg = 7'b0100100;
            4'd6: seg = 7'b0100000;
            4'd7: seg = 7'b0001111;
            4'd8: seg = 7'b0000000;  // all on
            4'd9: seg = 7'b0000100;
            default: seg = 7'b1111111;  // all off
        endcase
    end
endmodule

module stopwatch_counter(
    input clk, start, stop, reset,
    output reg [3:0] sec_ones, sec_tens, min_ones, min_tens
);
    reg running = 0;

    always @(posedge clk or posedge reset) begin
        if (reset) begin
            sec_ones <= 0; sec_tens <= 0;
            min_ones <= 0; min_tens <= 0;
            running <= 0;
        end else begin
            if (start) running <= 1;
            if (stop) running <= 0;

            if (running) begin
                sec_ones <= sec_ones + 1;
                if (sec_ones == 9) begin
                    sec_ones <= 0;
                    sec_tens <= sec_tens + 1;
                end
                if (sec_tens == 5 && sec_ones == 9) begin
                    sec_tens <= 0;
                    min_ones <= min_ones + 1;
                end
                if (min_ones == 9 && sec_tens == 5 && sec_ones == 9) begin
                    min_ones <= 0;
                    min_tens <= min_tens + 1;
                end
            end
        end
    end
endmodule


module display_mux(
    input clk,  
    input [3:0] d0, d1, d2, d3,
    output reg [3:0] an, //active low enable
    output reg [3:0] digit
);
    reg [1:0] sel = 0;

    always @(posedge clk) begin
        sel <= sel + 1;
        case (sel)
            2'b00: begin an = 4'b1110; digit = d0; end
            2'b01: begin an = 4'b1101; digit = d1; end
            2'b10: begin an = 4'b1011; digit = d2; end
            2'b11: begin an = 4'b0111; digit = d3; end
        endcase
    end
endmodule

module top(
    input clk,
    input btn_start, btn_stop, btn_reset,
    output [6:0] seg,
    output [3:0] an
);
    wire clk_1hz, clk_khz;
    wire [3:0] s1, s2, m1, m2;
    wire [3:0] digit;

    clk_divider clkdiv(clk, btn_reset, clk_1hz, clk_khz);
    stopwatch_counter sw(clk_1hz, btn_start, btn_stop, btn_reset, s1, s2, m1, m2);
    display_mux disp(clk_khz, s1, s2, m1, m2, an, digit);
    seven_segment_decoder dec(digit, seg);
endmodule

module stopwatch_tb;
  reg clk = 0;
  reg reset = 1;
  reg start = 0;
  reg stop = 0;
  wire [6:0] seg;
  wire [3:0] an;

  // Instantiate the design
  top uut (
    .clk(clk),
    .btn_reset(reset),
    .btn_start(start),
    .btn_stop(stop),
    .seg(seg),
    .an(an)
  );

  // Clock generation
  always #5 clk = ~clk; 

  initial begin
    
    $dumpfile("waveform.vcd");
    $dumpvars(0, stopwatch_tb);

    #10 reset = 0;   // Release reset
    #20 start = 1;   // Start stopwatch
    #500 start = 0;  
    #1000 stop = 1;
    #100 stop = 0;

    #500 $finish;
  end
endmodule

waveform.vcd
$date
	Tue Jun 24 12:56:23 2025
$end
$version
	Icarus Verilog
$end
$timescale
	1ps
$end
$scope module stopwatch_tb $end
$var wire 7 ! seg [6:0] $end
$var wire 4 " an [3:0] $end
$var reg 1 # clk $end
$var reg 1 $ reset $end
$var reg 1 % start $end
$var reg 1 & stop $end
$scope module uut $end
$var wire 1 $ btn_reset $end
$var wire 1 % btn_start $end
$var wire 1 & btn_stop $end
$var wire 1 # clk $end
$var wire 7 ' seg [6:0] $end
$var wire 4 ( s2 [3:0] $end
$var wire 4 ) s1 [3:0] $end
$var wire 4 * m2 [3:0] $end
$var wire 4 + m1 [3:0] $end
$var wire 4 , digit [3:0] $end
$var wire 1 - clk_khz $end
$var wire 1 . clk_1hz $end
$var wire 4 / an [3:0] $end
$scope module clkdiv $end
$var wire 1 # clk $end
$var wire 1 $ reset $end
$var reg 1 . clk_1hz $end
$var reg 1 - clk_khz $end
$var reg 27 0 count_hz [26:0] $end
$var reg 17 1 count_khz [16:0] $end
$upscope $end
$scope module dec $end
$var wire 4 2 digit [3:0] $end
$var reg 7 3 seg [6:0] $end
$upscope $end
$scope module disp $end
$var wire 1 - clk $end
$var wire 4 4 d3 [3:0] $end
$var wire 4 5 d2 [3:0] $end
$var wire 4 6 d1 [3:0] $end
$var wire 4 7 d0 [3:0] $end
$var reg 4 8 an [3:0] $end
$var reg 4 9 digit [3:0] $end
$var reg 2 : sel [1:0] $end
$upscope $end
$scope module sw $end
$var wire 1 . clk $end
$var wire 1 $ reset $end
$var wire 1 % start $end
$var wire 1 & stop $end
$var reg 4 ; min_ones [3:0] $end
$var reg 4 < min_tens [3:0] $end
$var reg 1 = running $end
$var reg 4 > sec_ones [3:0] $end
$var reg 4 ? sec_tens [3:0] $end
$upscope $end
$upscope $end
$upscope $end
$enddefinitions $end
$comment Show the parameter values. $end
$dumpall
$end
#0
$dumpvars
b0 ?
b0 >
0=
b0 <
b0 ;
b0 :
bx 9
bx 8
b0 7
b0 6
b0 5
b0 4
bx 3
bx 2
b0 1
b0 0
bx /
0.
0-
bx ,
b0 +
b0 *
b0 )
b0 (
bx '
0&
0%
1$
0#
bx "
bx !
$end
#5000
1#
#10000
0#
0$
#15000
b1 0
b1 1
1#
#20000
0#
#25000
b10 1
b10 0
1#
#30000
0#
1%
#35000
b1 :
b1 !
b1 '
b1 3
b0 ,
b0 2
b0 9
b1110 "
b1110 /
b1110 8
b11 0
1-
b0 1
1#
#40000
0#
#45000
b1 1
b100 0
1#
#50000
0#
#55000
b101 0
b10 1
1#
#60000
0#
#65000
1=
0-
b0 1
1.
b0 0
1#
#70000
0#
#75000
b1 0
b1 1
1#
#80000
0#
#85000
b10 1
b10 0
1#
#90000
0#
#95000
b10 :
b1101 "
b1101 /
b1101 8
b11 0
1-
b0 1
1#
#100000
0#
#105000
b1 1
b100 0
1#
#110000
0#
#115000
b101 0
b10 1
1#
#120000
0#
#125000
0-
b0 1
0.
b0 0
1#
#130000
0#
#135000
b1 0
b1 1
1#
#140000
0#
#145000
b10 1
b10 0
1#
#150000
0#
#155000
b11 :
b1011 "
b1011 /
b1011 8
b11 0
1-
b0 1
1#
#160000
0#
#165000
b1 1
b100 0
1#
#170000
0#
#175000
b101 0
b10 1
1#
#180000
0#
#185000
b1 )
b1 7
b1 >
0-
b0 1
1.
b0 0
1#
#190000
0#
#195000
b1 0
b1 1
1#
#200000
0#
#205000
b10 1
b10 0
1#
#210000
0#
#215000
b0 :
b111 "
b111 /
b111 8
b11 0
1-
b0 1
1#
#220000
0#
#225000
b1 1
b100 0
1#
#230000
0#
#235000
b101 0
b10 1
1#
#240000
0#
#245000
0-
b0 1
0.
b0 0
1#
#250000
0#
#255000
b1 0
b1 1
1#
#260000
0#
#265000
b10 1
b10 0
1#
#270000
0#
#275000
b1 :
b1001111 !
b1001111 '
b1001111 3
b1 ,
b1 2
b1 9
b1110 "
b1110 /
b1110 8
b11 0
1-
b0 1
1#
#280000
0#
#285000
b1 1
b100 0
1#
#290000
0#
#295000
b101 0
b10 1
1#
#300000
0#
#305000
b10 )
b10 7
b10 >
0-
b0 1
1.
b0 0
1#
#310000
0#
#315000
b1 0
b1 1
1#
#320000
0#
#325000
b10 1
b10 0
1#
#330000
0#
#335000
b10 :
b1 !
b1 '
b1 3
b0 ,
b0 2
b0 9
b1101 "
b1101 /
b1101 8
b11 0
1-
b0 1
1#
#340000
0#
#345000
b1 1
b100 0
1#
#350000
0#
#355000
b101 0
b10 1
1#
#360000
0#
#365000
0-
b0 1
0.
b0 0
1#
#370000
0#
#375000
b1 0
b1 1
1#
#380000
0#
#385000
b10 1
b10 0
1#
#390000
0#
#395000
b11 :
b1011 "
b1011 /
b1011 8
b11 0
1-
b0 1
1#
#400000
0#
#405000
b1 1
b100 0
1#
#410000
0#
#415000
b101 0
b10 1
1#
#420000
0#
#425000
b11 )
b11 7
b11 >
0-
b0 1
1.
b0 0
1#
#430000
0#
#435000
b1 0
b1 1
1#
#440000
0#
#445000
b10 1
b10 0
1#
#450000
0#
#455000
b0 :
b111 "
b111 /
b111 8
b11 0
1-
b0 1
1#
#460000
0#
#465000
b1 1
b100 0
1#
#470000
0#
#475000
b101 0
b10 1
1#
#480000
0#
#485000
0-
b0 1
0.
b0 0
1#
#490000
0#
#495000
b1 0
b1 1
1#
#500000
0#
#505000
b10 1
b10 0
1#
#510000
0#
#515000
b1 :
b110 !
b110 '
b110 3
b11 ,
b11 2
b11 9
b1110 "
b1110 /
b1110 8
b11 0
1-
b0 1
1#
#520000
0#
#525000
b1 1
b100 0
1#
#530000
0#
0%
#535000
b101 0
b10 1
1#
#540000
0#
#545000
b100 )
b100 7
b100 >
0-
b0 1
1.
b0 0
1#
#550000
0#
#555000
b1 0
b1 1
1#
#560000
0#
#565000
b10 1
b10 0
1#
#570000
0#
#575000
b10 :
b1 !
b1 '
b1 3
b0 ,
b0 2
b0 9
b1101 "
b1101 /
b1101 8
b11 0
1-
b0 1
1#
#580000
0#
#585000
b1 1
b100 0
1#
#590000
0#
#595000
b101 0
b10 1
1#
#600000
0#
#605000
0-
b0 1
0.
b0 0
1#
#610000
0#
#615000
b1 0
b1 1
1#
#620000
0#
#625000
b10 1
b10 0
1#
#630000
0#
#635000
b11 :
b1011 "
b1011 /
b1011 8
b11 0
1-
b0 1
1#
#640000
0#
#645000
b1 1
b100 0
1#
#650000
0#
#655000
b101 0
b10 1
1#
#660000
0#
#665000
b101 )
b101 7
b101 >
0-
b0 1
1.
b0 0
1#
#670000
0#
#675000
b1 0
b1 1
1#
#680000
0#
#685000
b10 1
b10 0
1#
#690000
0#
#695000
b0 :
b111 "
b111 /
b111 8
b11 0
1-
b0 1
1#
#700000
0#
#705000
b1 1
b100 0
1#
#710000
0#
#715000
b101 0
b10 1
1#
#720000
0#
#725000
0-
b0 1
0.
b0 0
1#
#730000
0#
#735000
b1 0
b1 1
1#
#740000
0#
#745000
b10 1
b10 0
1#
#750000
0#
#755000
b1 :
b100100 !
b100100 '
b100100 3
b101 ,
b101 2
b101 9
b1110 "
b1110 /
b1110 8
b11 0
1-
b0 1
1#
#760000
0#
#765000
b1 1
b100 0
1#
#770000
0#
#775000
b101 0
b10 1
1#
#780000
0#
#785000
b110 )
b110 7
b110 >
0-
b0 1
1.
b0 0
1#
#790000
0#
#795000
b1 0
b1 1
1#
#800000
0#
#805000
b10 1
b10 0
1#
#810000
0#
#815000
b10 :
b1 !
b1 '
b1 3
b0 ,
b0 2
b0 9
b1101 "
b1101 /
b1101 8
b11 0
1-
b0 1
1#
#820000
0#
#825000
b1 1
b100 0
1#
#830000
0#
#835000
b101 0
b10 1
1#
#840000
0#
#845000
0-
b0 1
0.
b0 0
1#
#850000
0#
#855000
b1 0
b1 1
1#
#860000
0#
#865000
b10 1
b10 0
1#
#870000
0#
#875000
b11 :
b1011 "
b1011 /
b1011 8
b11 0
1-
b0 1
1#
#880000
0#
#885000
b1 1
b100 0
1#
#890000
0#
#895000
b101 0
b10 1
1#
#900000
0#
#905000
b111 )
b111 7
b111 >
0-
b0 1
1.
b0 0
1#
#910000
0#
#915000
b1 0
b1 1
1#
#920000
0#
#925000
b10 1
b10 0
1#
#930000
0#
#935000
b0 :
b111 "
b111 /
b111 8
b11 0
1-
b0 1
1#
#940000
0#
#945000
b1 1
b100 0
1#
#950000
0#
#955000
b101 0
b10 1
1#
#960000
0#
#965000
0-
b0 1
0.
b0 0
1#
#970000
0#
#975000
b1 0
b1 1
1#
#980000
0#
#985000
b10 1
b10 0
1#
#990000
0#
#995000
b1 :
b1111 !
b1111 '
b1111 3
b111 ,
b111 2
b111 9
b1110 "
b1110 /
b1110 8
b11 0
1-
b0 1
1#
#1000000
0#
#1005000
b1 1
b100 0
1#
#1010000
0#
#1015000
b101 0
b10 1
1#
#1020000
0#
#1025000
b1000 )
b1000 7
b1000 >
0-
b0 1
1.
b0 0
1#
#1030000
0#
#1035000
b1 0
b1 1
1#
#1040000
0#
#1045000
b10 1
b10 0
1#
#1050000
0#
#1055000
b10 :
b1 !
b1 '
b1 3
b0 ,
b0 2
b0 9
b1101 "
b1101 /
b1101 8
b11 0
1-
b0 1
1#
#1060000
0#
#1065000
b1 1
b100 0
1#
#1070000
0#
#1075000
b101 0
b10 1
1#
#1080000
0#
#1085000
0-
b0 1
0.
b0 0
1#
#1090000
0#
#1095000
b1 0
b1 1
1#
#1100000
0#
#1105000
b10 1
b10 0
1#
#1110000
0#
#1115000
b11 :
b1011 "
b1011 /
b1011 8
b11 0
1-
b0 1
1#
#1120000
0#
#1125000
b1 1
b100 0
1#
#1130000
0#
#1135000
b101 0
b10 1
1#
#1140000
0#
#1145000
b1001 )
b1001 7
b1001 >
0-
b0 1
1.
b0 0
1#
#1150000
0#
#1155000
b1 0
b1 1
1#
#1160000
0#
#1165000
b10 1
b10 0
1#
#1170000
0#
#1175000
b0 :
b111 "
b111 /
b111 8
b11 0
1-
b0 1
1#
#1180000
0#
#1185000
b1 1
b100 0
1#
#1190000
0#
#1195000
b101 0
b10 1
1#
#1200000
0#
#1205000
0-
b0 1
0.
b0 0
1#
#1210000
0#
#1215000
b1 0
b1 1
1#
#1220000
0#
#1225000
b10 1
b10 0
1#
#1230000
0#
#1235000
b1 :
b100 !
b100 '
b100 3
b1001 ,
b1001 2
b1001 9
b1110 "
b1110 /
b1110 8
b11 0
1-
b0 1
1#
#1240000
0#
#1245000
b1 1
b100 0
1#
#1250000
0#
#1255000
b101 0
b10 1
1#
#1260000
0#
#1265000
b1 (
b1 6
b1 ?
b0 )
b0 7
b0 >
0-
b0 1
1.
b0 0
1#
#1270000
0#
#1275000
b1 0
b1 1
1#
#1280000
0#
#1285000
b10 1
b10 0
1#
#1290000
0#
#1295000
b10 :
b1001111 !
b1001111 '
b1001111 3
b1 ,
b1 2
b1 9
b1101 "
b1101 /
b1101 8
b11 0
1-
b0 1
1#
#1300000
0#
#1305000
b1 1
b100 0
1#
#1310000
0#
#1315000
b101 0
b10 1
1#
#1320000
0#
#1325000
0-
b0 1
0.
b0 0
1#
#1330000
0#
#1335000
b1 0
b1 1
1#
#1340000
0#
#1345000
b10 1
b10 0
1#
#1350000
0#
#1355000
b11 :
b1 !
b1 '
b1 3
b0 ,
b0 2
b0 9
b1011 "
b1011 /
b1011 8
b11 0
1-
b0 1
1#
#1360000
0#
#1365000
b1 1
b100 0
1#
#1370000
0#
#1375000
b101 0
b10 1
1#
#1380000
0#
#1385000
b1 )
b1 7
b1 >
0-
b0 1
1.
b0 0
1#
#1390000
0#
#1395000
b1 0
b1 1
1#
#1400000
0#
#1405000
b10 1
b10 0
1#
#1410000
0#
#1415000
b0 :
b111 "
b111 /
b111 8
b11 0
1-
b0 1
1#
#1420000
0#
#1425000
b1 1
b100 0
1#
#1430000
0#
#1435000
b101 0
b10 1
1#
#1440000
0#
#1445000
0-
b0 1
0.
b0 0
1#
#1450000
0#
#1455000
b1 0
b1 1
1#
#1460000
0#
#1465000
b10 1
b10 0
1#
#1470000
0#
#1475000
b1 :
b1001111 !
b1001111 '
b1001111 3
b1 ,
b1 2
b1 9
b1110 "
b1110 /
b1110 8
b11 0
1-
b0 1
1#
#1480000
0#
#1485000
b1 1
b100 0
1#
#1490000
0#
#1495000
b101 0
b10 1
1#
#1500000
0#
#1505000
b10 )
b10 7
b10 >
0-
b0 1
1.
b0 0
1#
#1510000
0#
#1515000
b1 0
b1 1
1#
#1520000
0#
#1525000
b10 1
b10 0
1#
#1530000
0#
1&
#1535000
b10 :
b1101 "
b1101 /
b1101 8
b11 0
1-
b0 1
1#
#1540000
0#
#1545000
b1 1
b100 0
1#
#1550000
0#
#1555000
b101 0
b10 1
1#
#1560000
0#
#1565000
0-
b0 1
0.
b0 0
1#
#1570000
0#
#1575000
b1 0
b1 1
1#
#1580000
0#
#1585000
b10 1
b10 0
1#
#1590000
0#
#1595000
b11 :
b1 !
b1 '
b1 3
b0 ,
b0 2
b0 9
b1011 "
b1011 /
b1011 8
b11 0
1-
b0 1
1#
#1600000
0#
#1605000
b1 1
b100 0
1#
#1610000
0#
#1615000
b101 0
b10 1
1#
#1620000
0#
#1625000
b11 )
b11 7
b11 >
0=
0-
b0 1
1.
b0 0
1#
#1630000
0#
0&
#1635000
b1 0
b1 1
1#
#1640000
0#
#1645000
b10 1
b10 0
1#
#1650000
0#
#1655000
b0 :
b111 "
b111 /
b111 8
b11 0
1-
b0 1
1#
#1660000
0#
#1665000
b1 1
b100 0
1#
#1670000
0#
#1675000
b101 0
b10 1
1#
#1680000
0#
#1685000
0-
b0 1
0.
b0 0
1#
#1690000
0#
#1695000
b1 0
b1 1
1#
#1700000
0#
#1705000
b10 1
b10 0
1#
#1710000
0#
#1715000
b1 :
b110 !
b110 '
b110 3
b11 ,
b11 2
b11 9
b1110 "
b1110 /
b1110 8
b11 0
1-
b0 1
1#
#1720000
0#
#1725000
b1 1
b100 0
1#
#1730000
0#
#1735000
b101 0
b10 1
1#
#1740000
0#
#1745000
0-
b0 1
1.
b0 0
1#
#1750000
0#
#1755000
b1 0
b1 1
1#
#1760000
0#
#1765000
b10 1
b10 0
1#
#1770000
0#
#1775000
b10 :
b1001111 !
b1001111 '
b1001111 3
b1 ,
b1 2
b1 9
b1101 "
b1101 /
b1101 8
b11 0
1-
b0 1
1#
#1780000
0#
#1785000
b1 1
b100 0
1#
#1790000
0#
#1795000
b101 0
b10 1
1#
#1800000
0#
#1805000
0-
b0 1
0.
b0 0
1#
#1810000
0#
#1815000
b1 0
b1 1
1#
#1820000
0#
#1825000
b10 1
b10 0
1#
#1830000
0#
#1835000
b11 :
b1 !
b1 '
b1 3
b0 ,
b0 2
b0 9
b1011 "
b1011 /
b1011 8
b11 0
1-
b0 1
1#
#1840000
0#
#1845000
b1 1
b100 0
1#
#1850000
0#
#1855000
b101 0
b10 1
1#
#1860000
0#
#1865000
0-
b0 1
1.
b0 0
1#
#1870000
0#
#1875000
b1 0
b1 1
1#
#1880000
0#
#1885000
b10 1
b10 0
1#
#1890000
0#
#1895000
b0 :
b111 "
b111 /
b111 8
b11 0
1-
b0 1
1#
#1900000
0#
#1905000
b1 1
b100 0
1#
#1910000
0#
#1915000
b101 0
b10 1
1#
#1920000
0#
#1925000
0-
b0 1
0.
b0 0
1#
#1930000
0#
#1935000
b1 0
b1 1
1#
#1940000
0#
#1945000
b10 1
b10 0
1#
#1950000
0#
#1955000
b1 :
b110 !
b110 '
b110 3
b11 ,
b11 2
b11 9
b1110 "
b1110 /
b1110 8
b11 0
1-
b0 1
1#
#1960000
0#
#1965000
b1 1
b100 0
1#
#1970000
0#
#1975000
b101 0
b10 1
1#
#1980000
0#
#1985000
0-
b0 1
1.
b0 0
1#
#1990000
0#
#1995000
b1 0
b1 1
1#
#2000000
0#
#2005000
b10 1
b10 0
1#
#2010000
0#
#2015000
b10 :
b1001111 !
b1001111 '
b1001111 3
b1 ,
b1 2
b1 9
b1101 "
b1101 /
b1101 8
b11 0
1-
b0 1
1#
#2020000
0#
#2025000
b1 1
b100 0
1#
#2030000
0#
#2035000
b101 0
b10 1
1#
#2040000
0#
#2045000
0-
b0 1
0.
b0 0
1#
#2050000
0#
#2055000
b1 0
b1 1
1#
#2060000
0#
#2065000
b10 1
b10 0
1#
#2070000
0#
#2075000
b11 :
b1 !
b1 '
b1 3
b0 ,
b0 2
b0 9
b1011 "
b1011 /
b1011 8
b11 0
1-
b0 1
1#
#2080000
0#
#2085000
b1 1
b100 0
1#
#2090000
0#
#2095000
b101 0
b10 1
1#
#2100000
0#
#2105000
0-
b0 1
1.
b0 0
1#
#2110000
0#
#2115000
b1 0
b1 1
1#
#2120000
0#
#2125000
b10 1
b10 0
1#
